gcp_python_client_functions/__init__.py
gcp_python_client_functions/_modidx.py
gcp_python_client_functions/clients.py
gcp_python_client_functions-0.0.1.dist-info/LICENSE
gcp_python_client_functions-0.0.1.dist-info/METADATA
gcp_python_client_functions-0.0.1.dist-info/WHEEL
gcp_python_client_functions-0.0.1.dist-info/entry_points.txt
gcp_python_client_functions-0.0.1.dist-info/top_level.txt
gcp_python_client_functions-0.0.1.dist-info/RECORD
