Metadata-Version: 2.1
Name: gcp-python-client-functions
Version: 0.0.1
Summary: One package that will handle the installation and client generation for the most used  GCP Python Client Libraries + methods that avoid repetitive processes.
Home-page: https://github.com/datasciencedani/gcp-python-client-functions
Author: Daniela Zamora
Author-email: danizhorta24@gmail.com
License: Apache Software License 2.0
Keywords: nbdev jupyter notebook python google api bigquery storage
Classifier: Development Status :: 4 - Beta
Classifier: Intended Audience :: Developers
Classifier: Natural Language :: English
Classifier: Programming Language :: Python :: 3.7
Classifier: Programming Language :: Python :: 3.8
Classifier: Programming Language :: Python :: 3.9
Classifier: Programming Language :: Python :: 3.10
Classifier: License :: OSI Approved :: Apache Software License
Requires-Python: >=3.7
License-File: LICENSE
Requires-Dist: google
Requires-Dist: google-cloud-bigquery
Requires-Dist: pandas
Requires-Dist: db-dtypes
Requires-Dist: fsspec
Requires-Dist: gcsfs
Requires-Dist: google-cloud-storage
Requires-Dist: fastcore
Provides-Extra: dev
Requires-Dist: google ; extra == 'dev'
Requires-Dist: google-cloud-bigquery ; extra == 'dev'
Requires-Dist: pandas ; extra == 'dev'
Requires-Dist: db-dtypes ; extra == 'dev'
Requires-Dist: fsspec ; extra == 'dev'
Requires-Dist: gcsfs ; extra == 'dev'
Requires-Dist: google-cloud-storage ; extra == 'dev'
Requires-Dist: fastcore ; extra == 'dev'
